<?xml version="1.0" encoding="UTF-8"?>
    <source package="sun.awt.X11">
        <import package="sun.misc.Unsafe"/>
        <class name="XQueryTree" line="32">
            <declaration name="unsafe" type="Unsafe" line="33"/>
            <declaration name="__executed" type="boolean" line="34"/>
            <declaration name="_w" type="long" line="35"/>
            <declaration name="root_ptr" type="long" line="36"/>
            <declaration name="parent_ptr" type="long" line="37"/>
            <declaration name="children_ptr" type="long" line="38"/>
            <declaration name="nchildren_ptr" type="long" line="39"/>
            <declaration name="disposer" type="UnsafeXDisposerRecord" line="40"/>
            <method name="XQueryTree" type="constructor" line="43">
                <params>
                    <param name="w" type="long"/>
                </params>
            </method>
            <method name="execute" type="int" line="50"/>
            <method name="execute" type="int" line="53">
                <params>
                    <param name="errorHandler" type="XErrorHandler"/>
                </params>
                <scope line="55">
                    <scope line="56"/>
                    <scope line="59"/>
                    <scope line="63"/>
                    <declaration name="status" type="int" line="67"/>
                    <scope line="74"/>
                </scope>
                <scope line="78"/>
            </method>
            <method name="isExecuted" type="boolean" line="82"/>
            <method name="isDisposed" type="boolean" line="86"/>
            <method name="dispose" type="void" line="89">
                <scope line="91">
                    <scope line="92"/>
                </scope>
                <scope line="96"/>
            </method>
            <method name="get_w" type="long" line="100">
                <scope line="101"/>
                <scope line="104"/>
            </method>
            <method name="set_w" type="void" line="109">
                <params>
                    <param name="data" type="long"/>
                </params>
            </method>
            <method name="get_root" type="long" line="112">
                <scope line="113"/>
                <scope line="116"/>
            </method>
            <method name="set_root" type="void" line="121">
                <params>
                    <param name="data" type="long"/>
                </params>
            </method>
            <method name="get_parent" type="long" line="124">
                <scope line="125"/>
                <scope line="128"/>
            </method>
            <method name="set_parent" type="void" line="133">
                <params>
                    <param name="data" type="long"/>
                </params>
            </method>
            <method name="get_children" type="long" line="136">
                <scope line="137"/>
                <scope line="140"/>
            </method>
            <method name="set_children" type="void" line="145">
                <params>
                    <param name="data" type="long"/>
                </params>
            </method>
            <method name="get_nchildren" type="int" line="148">
                <scope line="149"/>
                <scope line="152"/>
            </method>
            <method name="set_nchildren" type="void" line="157">
                <params>
                    <param name="data" type="int"/>
                </params>
            </method>
        </class>
    </source>