<?xml version="1.0" encoding="UTF-8"?>
<source package="org.apache.commons.math3.optim.univariate">
  <import name="org.apache.commons.math3.optim.OptimizationData" />
  <import name="org.apache.commons.math3.exception.NumberIsTooLargeException" />
  <import name="org.apache.commons.math3.exception.OutOfRangeException" />
  <class name="SearchInterval" startLine="23">
    <implements name="OptimizationData" />
    <javadoc>
      <text>* Search interval and (optional) start value.
 * <br/>
 * Immutable class.</text>
      <version>$Id: SearchInterval.java 1435539 2013-01-19 13:27:24Z tn $</version>
      <since>3.1</since>
    </javadoc>
    <javadoc>
      <text>* Lower bound.</text>
    </javadoc>
    <declaration type="double" name="lower" />
    <javadoc>
      <text>* Upper bound.</text>
    </javadoc>
    <declaration type="double" name="upper" />
    <javadoc>
      <text>* Start value.</text>
    </javadoc>
    <declaration type="double" name="start" />
    <javadoc>
      <param>lo Lower bound.</param>
      <param>hi Upper bound.</param>
      <param>init Start value.</param>
      <throws>NumberIsTooLargeException if {@code lo >= hi}.</throws>
      <throws>OutOfRangeException if {@code init < lo} or {@code init > hi}.</throws>
    </javadoc>
    <method type="constructor" name="SearchInterval" startLine="48" endLine="60">
      <scope startLine="49" endLine="51" />
      <scope startLine="53" endLine="55" />
    </method>
    <javadoc>
      <param>lo Lower bound.</param>
      <param>hi Upper bound.</param>
      <throws>NumberIsTooLargeException if {@code lo >= hi}.</throws>
    </javadoc>
    <method type="constructor" name="SearchInterval" startLine="68" endLine="70" />
    <javadoc>
      <text>* Gets the lower bound.</text>
      <return>the lower bound.</return>
    </javadoc>
    <method type="double" name="getMin" startLine="77" endLine="79" />
    <javadoc>
      <text>* Gets the upper bound.</text>
      <return>the upper bound.</return>
    </javadoc>
    <method type="double" name="getMax" startLine="85" endLine="87" />
    <javadoc>
      <text>* Gets the start value.</text>
      <return>the start value.</return>
    </javadoc>
    <method type="double" name="getStartValue" startLine="93" endLine="95" />
  </class>
</source>
