<?xml version="1.0" encoding="UTF-8"?>
    <source package="sun.nio.fs">
        <import package="java.nio.file.attribute"/>
        <import package="java.util"/>
        <import package="java.io.IOException"/>
        <import package="sun.nio.fs.WindowsNativeDispatcher"/>
        <import package="sun.nio.fs.WindowsConstants"/>
        <class name="WindowsFileAttributeViews" line="7">
            <class name="Basic" line="8">
                <extends class="AbstractBasicFileAttributeView"/>
                <declaration name="file" type="WindowsPath" line="9"/>
                <declaration name="followLinks" type="boolean" line="10"/>
                <method name="Basic" type="constructor" line="11">
                    <params>
                        <param name="file" type="WindowsPath"/>
                        <param name="followLinks" type="boolean"/>
                    </params>
                </method>
                <method name="readAttributes" type="WindowsFileAttributes" line="15">
                    <scope line="17"/>
                    <scope line="20"/>
                </method>
                <javadoc line="25">
                    Adjusts a Windows time for the FAT epoch.                    
                </javadoc>
                <method name="adjustForFatEpoch" type="long" line="28">
                    <params>
                        <param name="time" type="long"/>
                    </params>
                    <declaration name="FAT_EPOCH" type="long" line="29"/>
                    <scope line="30"/>
                    <scope line="33"/>
                </method>
                <javadoc line="37">
                    Parameter values in Windows times.                    
                </javadoc>
                <method name="setFileTimes" type="void" line="40">
                    <params>
                        <param name="createTime" type="long"/>
                        <param name="lastAccessTime" type="long"/>
                        <param name="lastWriteTime" type="long"/>
                    </params>
                    <declaration name="handle" type="long" line="41"/>
                    <scope line="42">
                        <declaration name="flags" type="int" line="43"/>
                    </scope>
                    <scope line="47"/>
                    <scope line="50"/>
                    <scope line="53">
                        <scope line="54">
                            <scope line="55">
                                <scope line="56"/>
                            </scope>
                            <scope line="61"/>
                            <scope line="63"/>
                            <scope line="65"/>
                        </scope>
                    </scope>
                    <scope line="70"/>
                </method>
                <method name="setTimes" type="void" line="74">
                    <params>
                        <param name="lastModifiedTime" type="FileTime"/>
                        <param name="lastAccessTime" type="FileTime"/>
                        <param name="createTime" type="FileTime"/>
                    </params>
                    <scope line="75"/>
                    <declaration name="t1" type="long" line="79"/>
                    <declaration name="t2" type="long" line="80"/>
                    <declaration name="t3" type="long" line="81"/>
                </method>
            </class>
            <class name="Dos" line="85">
                <extends class="Basic"/>
                <implements interface="DosFileAttributeView"/>
                <declaration name="READONLY_NAME" type="String" line="86"/>
                <declaration name="ARCHIVE_NAME" type="String" line="87"/>
                <declaration name="SYSTEM_NAME" type="String" line="88"/>
                <declaration name="HIDDEN_NAME" type="String" line="89"/>
                <declaration name="ATTRIBUTES_NAME" type="String" line="90"/>
                <declaration name="dosAttributeNames" type="Set&lt;String&gt;" line="91"/>
                <method name="Dos" type="constructor" line="92">
                    <params>
                        <param name="file" type="WindowsPath"/>
                        <param name="followLinks" type="boolean"/>
                    </params>
                </method>
                <method name="name" type="String" line="95"/>
                <method name="setAttribute" type="void" line="98">
                    <params>
                        <param name="attribute" type="String"/>
                        <param name="value" type="Object"/>
                    </params>
                    <scope line="99"/>
                    <scope line="103"/>
                    <scope line="107"/>
                    <scope line="111"/>
                </method>
                <method name="readAttributes" type="Map<String,Object>" line="117">
                    <params>
                        <param name="attributes" type="String[]"/>
                    </params>
                    <declaration name="builder" type="AttributesBuilder" line="118"/>
                    <declaration name="attrs" type="WindowsFileAttributes" line="119"/>
                </method>
                <javadoc line="128">
                    Update DOS attributes                    
                </javadoc>
                <method name="updateAttributes" type="void" line="131">
                    <params>
                        <param name="flag" type="int"/>
                        <param name="enable" type="boolean"/>
                    </params>
                    <declaration name="path" type="String" line="133"/>
                    <scope line="134">
                        <declaration name="oldValue" type="int" line="135"/>
                        <declaration name="newValue" type="int" line="136"/>
                        <scope line="137"/>
                        <scope line="140"/>
                        <scope line="143"/>
                    </scope>
                    <scope line="147"/>
                </method>
                <method name="setReadOnly" type="void" line="151">
                    <params>
                        <param name="value" type="boolean"/>
                    </params>
                </method>
                <method name="setHidden" type="void" line="154">
                    <params>
                        <param name="value" type="boolean"/>
                    </params>
                </method>
                <method name="setArchive" type="void" line="157">
                    <params>
                        <param name="value" type="boolean"/>
                    </params>
                </method>
                <method name="setSystem" type="void" line="160">
                    <params>
                        <param name="value" type="boolean"/>
                    </params>
                </method>
                <method name="setAttributes" type="void" line="163">
                    <params>
                        <param name="attrs" type="WindowsFileAttributes"/>
                    </params>
                    <declaration name="flags" type="int" line="164"/>
                </method>
            </class>
            <method name="createBasicView" type="Basic" line="173">
                <params>
                    <param name="file" type="WindowsPath"/>
                    <param name="followLinks" type="boolean"/>
                </params>
            </method>
            <method name="createDosView" type="Dos" line="176">
                <params>
                    <param name="file" type="WindowsPath"/>
                    <param name="followLinks" type="boolean"/>
                </params>
            </method>
        </class>
    </source>