<?xml version="1.0" encoding="UTF-8"?>
    <source package="no.uib.cipr.matrix">
        <class name="NotConvergedException" line="23">
            <extends class="Exception"/>
            <javadoc line="23">
                Signals lack of convergence of an iterative process                
            </javadoc>
            <declaration name="serialVersionUID" type="long" line="28"/>
            <declaration name="Reason" type="enum" line="30"/>
            <javadoc line="30">
                Possible reasons for lack of convergence                
            </javadoc>
            <scope line="33"/>
            <declaration name="reason" type="Reason" line="51"/>
            <javadoc line="51">
                The reason for this exception                
            </javadoc>
            <javadoc line="56">
                Constructor for NotConvergedException                
                <param>
                    reasonThe reason for the lack of convergence                    
                </param>
                <param>
                    messageA more descriptive explanation                    
                </param>
            </javadoc>
            <method name="NotConvergedException" type="constructor" line="64">
                <params>
                    <param name="reason" type="Reason"/>
                    <param name="message" type="String"/>
                </params>
            </method>
            <javadoc line="69">
                Constructor for NotConvergedException. No message is provided                
                <param>
                    reasonThe reason for the lack of convergence                    
                </param>
            </javadoc>
            <method name="NotConvergedException" type="constructor" line="75">
                <params>
                    <param name="reason" type="Reason"/>
                </params>
            </method>
            <javadoc line="79">
                Returns the reason for the exception                
            </javadoc>
            <method name="getReason" type="Reason" line="82"/>
        </class>
    </source>