<?xml version="1.0" encoding="UTF-8"?>
<source package="org.ojalgo.machine">
  <import name="java.lang.reflect.Field" />
  <import name="java.lang.reflect.Modifier" />
  <class name="MemoryEstimator" startLine="27">
    <javadoc>
      <text>* MemoryEstimator</text>
      <author>apete</author>
    </javadoc>
    <declaration type="long" name="FINAL_ALIGNEMENT" />
    <declaration type="long" name="PARENT_ALIGNEMENT" />
    <declaration type="long" name="WORD" />
    <declaration type="long" name="ZERO" />
    <method type="long" name="estimateArray" startLine="39" endLine="48">
      <declaration type="MemoryEstimator" name="tmpEstimator" />
    </method>
    <method type="long" name="estimateObject" startLine="50" endLine="52" />
    <method type="MemoryEstimator" name="makeForClassExtendingObject" startLine="54" endLine="56" />
    <method type="MemoryEstimator" name="makeForSubclass" startLine="58" endLine="60" />
    <method type="MemoryEstimator" name="make" startLine="62" endLine="86">
      <declaration type="MemoryEstimator" name="retVal" />
      <declaration type="Class<?>" name="tmpParent" />
      <scope startLine="68" endLine="70" />
      <scope startLine="70" endLine="73">
        <declaration type="MemoryEstimator" name="tmpParentEstimation" />
      </scope>
      <scope startLine="75" endLine="83">
        <declaration type="int" name="tmpModifier" />
        <scope startLine="78" endLine="82">
          <declaration type="Class<?>" name="tmpType" />
        </scope>
      </scope>
    </method>
    <declaration type="long" name="myShallowSize" />
    <method type="constructor" name="MemoryEstimator" startLine="91" endLine="93" />
    <method type="constructor" name="MemoryEstimator" startLine="95" endLine="100" />
    <method type="MemoryEstimator" name="add" startLine="102" endLine="104" />
    <method type="MemoryEstimator" name="add" startLine="106" endLine="108" />
    <method type="long" name="estimate" startLine="110" endLine="112" />
    <method type="MemoryEstimator" name="add" startLine="114" endLine="117" />
    <method type="long" name="align" startLine="119" endLine="128">
      <declaration type="long" name="tmpRemainder" />
      <scope startLine="123" endLine="125" />
      <scope startLine="125" endLine="127" />
    </method>
  </class>
</source>
