<?xml version="1.0" encoding="UTF-8"?>
    <source package="sun.tools.java">
        <class name="CompilerError" line="28">
            <extends class="Error"/>
            <javadoc line="28">
                This exception is thrown when an internal compiler error occurs
                  WARNING: The contents of this source file are not part of any
                  supported API.  Code that depends on them does so at its own risk:
                  they are subject to change or removal without notice.                
            </javadoc>
            <declaration name="e" type="Throwable" line="38"/>
            <javadoc line="40">
                Constructor                
            </javadoc>
            <method name="CompilerError" type="constructor" line="43">
                <params>
                    <param name="msg" type="String"/>
                </params>
            </method>
            <javadoc line="48">
                Create an exception given another exception.                
            </javadoc>
            <method name="CompilerError" type="constructor" line="51">
                <params>
                    <param name="e" type="Exception"/>
                </params>
            </method>
            <method name="printStackTrace" type="void" line="56"/>
        </class>
    </source>