<?xml version="1.0" encoding="UTF-8"?>
    <source package="edu.umd.cs.piccolo.examples">
        <import package="java.awt.BasicStroke"/>
        <import package="java.awt.Color"/>
        <import package="edu.umd.cs.piccolo.PCanvas"/>
        <import package="edu.umd.cs.piccolo.nodes.PPath"/>
        <import package="edu.umd.cs.piccolo.nodes.PText"/>
        <import package="edu.umd.cs.piccolox.PFrame"/>
        <import package="edu.umd.cs.piccolox.util.PFixedWidthStroke"/>
        <class name="StrokeExample" line="9">
            <extends class="PFrame"/>
            <javadoc line="9">
                Stroke example.                
            </javadoc>
            <declaration name="serialVersionUID" type="long" line="13"/>
            <javadoc line="13">
                                
            </javadoc>
            <javadoc line="16">
                Create a new stroke example.                
            </javadoc>
            <method name="StrokeExample" type="constructor" line="19"/>
            <javadoc line="22">
                Create a new stroke example with the specified canvas.                
                <param>
                    canvas canvas                    
                </param>
            </javadoc>
            <method name="StrokeExample" type="constructor" line="26">
                <params>
                    <param name="canvas" type="PCanvas"/>
                </params>
            </method>
            <javadoc line="29">
                {@inheritDoc}                
            </javadoc>
            <method name="initialize" type="void" line="32">
                <declaration name="label" type="PText" line="33"/>
                <declaration name="rect" type="PPath" line="36"/>
                <declaration name="fixedWidthLabel" type="PText" line="39"/>
                <declaration name="fixedWidthRect0" type="PPath" line="42"/>
                <declaration name="fixedWidthRect1" type="PPath" line="45"/>
                <declaration name="fixedWidthRect2" type="PPath" line="48"/>
            </method>
            <javadoc line="58">
                Main.                
                <param>
                    args command line arguments                    
                </param>
            </javadoc>
            <method name="main" type="void" line="62">
                <params>
                    <param name="args" type="String[]"/>
                </params>
            </method>
        </class>
    </source>